limitless_sdk/__init__.py
limitless_sdk/approval.py
limitless_sdk/auth.py
limitless_sdk/cache.py
limitless_sdk/client.py
limitless_sdk/constants.py
limitless_sdk/orders.py
limitless_sdk/redemption.py
limitless_sdk/utils.py
limitless_sdk/websocket.py
py_limitless-0.1.1.dist-info/METADATA
py_limitless-0.1.1.dist-info/WHEEL
py_limitless-0.1.1.dist-info/RECORD
