Metadata-Version: 2.4
Name: py-limitless
Version: 0.1.1
Summary: Python SDK for trading on Limitless Exchange
Project-URL: Homepage, https://limitless.exchange
Project-URL: Documentation, https://github.com/ego-errante/limitless-sdk#readme
Project-URL: Repository, https://github.com/ego-errante/limitless-sdk
Project-URL: Issues, https://github.com/ego-errante/limitless-sdk/issues
Author: Limitless SDK Contributors
License: MIT
Keywords: base,defi,ethereum,limitless,prediction-market,sdk,trading,web3
Classifier: Development Status :: 4 - Beta
Classifier: Intended Audience :: Developers
Classifier: License :: OSI Approved :: MIT License
Classifier: Operating System :: OS Independent
Classifier: Programming Language :: Python :: 3
Classifier: Programming Language :: Python :: 3.10
Classifier: Programming Language :: Python :: 3.11
Classifier: Programming Language :: Python :: 3.12
Classifier: Topic :: Office/Business :: Financial :: Investment
Classifier: Topic :: Software Development :: Libraries :: Python Modules
Requires-Python: >=3.10
Requires-Dist: aiohttp>=3.8
Requires-Dist: eth-abi>=4.0
Requires-Dist: eth-account==0.10.0
Requires-Dist: eth-utils>=2.0
Requires-Dist: python-dotenv>=1.0
Requires-Dist: python-socketio[asyncio-client]>=5.0
Requires-Dist: requests>=2.28
Requires-Dist: web3>=6.0
Provides-Extra: dev
Requires-Dist: black>=23.0; extra == 'dev'
Requires-Dist: pytest-asyncio>=0.21; extra == 'dev'
Requires-Dist: pytest>=7.0; extra == 'dev'
Requires-Dist: ruff>=0.1; extra == 'dev'
